jupyter_slurm_provisioner_extension/__init__.py
jupyter_slurm_provisioner_extension/_version.py
jupyter_slurm_provisioner_extension/handlers.py
jupyter_slurm_provisioner_extension/handlers_orig.py
jupyter_slurm_provisioner_extension/jupyter-slurm-provisioner-extension-handlers.py
jupyter_slurm_provisioner_extension-0.4.0.data/data/etc/jupyter/jupyter_server_config.d/jupyter_slurm_provisioner_extension.json
jupyter_slurm_provisioner_extension-0.4.0.data/data/share/jupyter/labextensions/jupyter-slurm-provisioner-extension/build_log.json
jupyter_slurm_provisioner_extension-0.4.0.data/data/share/jupyter/labextensions/jupyter-slurm-provisioner-extension/package.json
jupyter_slurm_provisioner_extension-0.4.0.data/data/share/jupyter/labextensions/jupyter-slurm-provisioner-extension/static/lib_index_js.b87d083951e3a26961de.js
jupyter_slurm_provisioner_extension-0.4.0.data/data/share/jupyter/labextensions/jupyter-slurm-provisioner-extension/static/lib_index_js.b87d083951e3a26961de.js.map
jupyter_slurm_provisioner_extension-0.4.0.data/data/share/jupyter/labextensions/jupyter-slurm-provisioner-extension/static/remoteEntry.e04bb9504ed3fa3c6f17.js
jupyter_slurm_provisioner_extension-0.4.0.data/data/share/jupyter/labextensions/jupyter-slurm-provisioner-extension/static/remoteEntry.e04bb9504ed3fa3c6f17.js.map
jupyter_slurm_provisioner_extension-0.4.0.data/data/share/jupyter/labextensions/jupyter-slurm-provisioner-extension/static/style.js
jupyter_slurm_provisioner_extension-0.4.0.data/data/share/jupyter/labextensions/jupyter-slurm-provisioner-extension/static/style_index_js.44873dc573b0c36f13cc.js
jupyter_slurm_provisioner_extension-0.4.0.data/data/share/jupyter/labextensions/jupyter-slurm-provisioner-extension/static/style_index_js.44873dc573b0c36f13cc.js.map
jupyter_slurm_provisioner_extension-0.4.0.dist-info/METADATA
jupyter_slurm_provisioner_extension-0.4.0.dist-info/WHEEL
jupyter_slurm_provisioner_extension-0.4.0.dist-info/licenses/LICENSE
jupyter_slurm_provisioner_extension-0.4.0.dist-info/RECORD
