Metadata-Version: 2.4
Name: jupyter_slurm_provisioner_extension
Version: 0.4.0
Dynamic: Keywords
Summary: Configure the Slurm kernel in JupyterLab
Project-URL: Homepage, https://github.com/FZJ-JSC/jupyter-slurm-provisioner-extension
Project-URL: Bug Tracker, https://github.com/FZJ-JSC/jupyter-slurm-provisioner-extension/issues
Project-URL: Repository, https://github.com/FZJ-JSC/jupyter-slurm-provisioner-extension.git
Author-email: Tim Kreuzer <t.kreuzer@fz-juelich.de>
License: MIT License
License-File: LICENSE
Classifier: Framework :: Jupyter
Classifier: Framework :: Jupyter :: JupyterLab
Classifier: Framework :: Jupyter :: JupyterLab :: 4
Classifier: Framework :: Jupyter :: JupyterLab :: Extensions
Classifier: Framework :: Jupyter :: JupyterLab :: Extensions :: Prebuilt
Classifier: License :: OSI Approved :: BSD License
Classifier: Programming Language :: Python
Classifier: Programming Language :: Python :: 3
Classifier: Programming Language :: Python :: 3.8
Classifier: Programming Language :: Python :: 3.9
Classifier: Programming Language :: Python :: 3.10
Classifier: Programming Language :: Python :: 3.11
Classifier: Programming Language :: Python :: 3.12
Requires-Python: >=3.8
Requires-Dist: jupyter-server<3,>=2.0.1
Requires-Dist: jupyter-slurm-provisioner
